tencent/cloud/core/__init__.py
tencent/cloud/core/client.py
tencent/cloud/core/errors.py
tencent/cloud/core/helper.py
tencent/cloud/core/proxies.py
tencent/cloud/core/version.py
tencent/cloud/core/waitable.py
tencent_cloud_sdk_core-0.2.6.dist-info/LICENSE
tencent_cloud_sdk_core-0.2.6.dist-info/METADATA
tencent_cloud_sdk_core-0.2.6.dist-info/WHEEL
tencent_cloud_sdk_core-0.2.6.dist-info/top_level.txt
tencent_cloud_sdk_core-0.2.6.dist-info/RECORD
