Metadata-Version: 2.1
Name: tencent-cloud-sdk-core
Version: 0.2.6
Summary: Tencent Cloud SDK for Python components. This package is the core component of the Tencent Cloud SDK. Most Tencent Cloud SDK components depend on this package.
Home-page: https://github.com/nobody-night/tencent-cloud-sdk-python
Author: MIEK
Author-email: king@xiaoyy.org
License: MIT License
Keywords: tencent-cloud sdk-python
Classifier: Programming Language :: Python :: 3.6
Classifier: License :: OSI Approved :: MIT License
Classifier: Operating System :: OS Independent
Classifier: Development Status :: 5 - Production/Stable
Requires-Python: >=3.6
License-File: LICENSE
Requires-Dist: tencent-cloud-sdk-auth (>=0.2.2)
Requires-Dist: tencent-cloud-sdk-common (>=0.1.5)
